exptool/__init__.py
exptool/check.py
exptool/named_tensor.py
exptool-1.0.0.dist-info/LICENSE
exptool-1.0.0.dist-info/METADATA
exptool-1.0.0.dist-info/WHEEL
exptool-1.0.0.dist-info/top_level.txt
exptool-1.0.0.dist-info/RECORD
